{"cameraMode":{"drawMode":0,"name":"Shaded","section":"Shading Mode"},"sceneLighting":true,"audioPlay":false,"sceneViewState":{"m_AlwaysRefresh":false,"showFog":true,"showSkybox":true,"showFlares":true,"showImageEffects":true,"showParticleSystems":true,"showVisualEffectGraphs":true,"m_FxEnabled":true},"in2DMode":false,"pivot":{"x":-35.22607421875,"y":2.132081985473633,"z":-1.7173596620559693},"rotation":{"x":0.1478997766971588,"y":-0.6983456611633301,"z":0.1510387659072876,"w":0.6838322877883911},"size":5.169511318206787,"orthographic":false}